LICENSE.md
MANIFEST.in
README.md
pyproject.toml
setup.cfg
setup.py
pytreedb_server/__init__.py
pytreedb_server/__main__.py
pytreedb_server.egg-info/PKG-INFO
pytreedb_server.egg-info/SOURCES.txt
pytreedb_server.egg-info/dependency_links.txt
pytreedb_server.egg-info/requires.txt
pytreedb_server.egg-info/top_level.txt
pytreedb_server/static/PicAbi_KA09_P2T2_indent2.json.html
pytreedb_server/static/dl_script.py
pytreedb_server/static/img/3dgeo.ico
pytreedb_server/static/img/3dgeo_logo.jpg
pytreedb_server/static/img/EjbXdeCWsAMUEZ9.jpg
pytreedb_server/static/img/IFGG_short_fat3.png
pytreedb_server/static/img/QR.png
pytreedb_server/static/img/geojson-template.png
pytreedb_server/static/img/pytreedb_logo_low.png
pytreedb_server/static/img/pytreedb_logo_low_w.png
pytreedb_server/static/js/jquery.json-viewer.js
pytreedb_server/static/js/jszip.min.js
pytreedb_server/static/js/script.js
pytreedb_server/static/styles/bootstrap.css
pytreedb_server/static/styles/jquery.json-viewer.css
pytreedb_server/static/styles/style.css
pytreedb_server/templates/3DGeo_Logo_transparent_bg.png
pytreedb_server/templates/about.html
pytreedb_server/templates/contact.html
pytreedb_server/templates/data-tree.css
pytreedb_server/templates/data-tree.js
pytreedb_server/templates/index.html
pytreedb_server/templates/jqtree.css
pytreedb_server/templates/tree.jquery.js
pytreedb_server/test/__init__.py
pytreedb_server/test/test_api.py