Metadata-Version: 2.1
Name: pytreedb-server
Version: 1.0.0.post1
Summary: server for providing API access to pytreedb
Author: 3DGeo Heidelberg
Author-email: hoefle@uni-heidelberg.de
License: (L)GPL License
Classifier: License :: OSI Approved :: GNU General Public License v3 or later (GPLv3+)
Classifier: License :: OSI Approved :: GNU Lesser General Public License v3 or later (LGPLv3+)
Classifier: Operating System :: OS Independent
Classifier: Programming Language :: Python :: 3
License-File: LICENSE.md
